obs_picamera/__init__.py
obs_picamera/api.py
obs_picamera/bluetooth.py
obs_picamera/py.typed
obs_picamera/recorder.py
obs_picamera/scripts/__init__.py
obs_picamera/scripts/obs_picamera.py
obs_picamera/scripts/ui.py
obs_picamera-0.2.0.dist-info/METADATA
obs_picamera-0.2.0.dist-info/entry_points.txt
obs_picamera-0.2.0.dist-info/WHEEL
obs_picamera-0.2.0.dist-info/RECORD
