Metadata-Version: 2.1
Name: obs-picamera
Version: 0.2.0
Summary: A python module to record video of overtaking events to allow vehicle type identification of OpenBikeSensor overtaking events.
Home-page: https://gluap.github.io/obs-picamera
License: MIT
Author: gluap
Author-email: github@pgoergen.de
Requires-Python: >=3.9,<4.0
Classifier: Development Status :: 4 - Beta
Classifier: Intended Audience :: Developers
Classifier: License :: OSI Approved :: MIT License
Classifier: Operating System :: OS Independent
Classifier: Programming Language :: Python
Classifier: Programming Language :: Python :: 3
Classifier: Programming Language :: Python :: 3.9
Classifier: Programming Language :: Python :: 3.10
Classifier: Programming Language :: Python :: 3.11
Classifier: Programming Language :: Python :: 3
Classifier: Programming Language :: Python :: 3.10
Classifier: Programming Language :: Python :: 3.11
Classifier: Programming Language :: Python :: 3.9
Classifier: Topic :: Software Development :: Libraries :: Python Modules
Classifier: Typing :: Typed
Requires-Dist: bleak (>=0.19.5)
Requires-Dist: fastapi (>0.89)
Requires-Dist: picamera2 (>=0.3.8)
Requires-Dist: remi (>=2022.7.27)
Requires-Dist: uvicorn (>=0.20)
Project-URL: Documentation, https://gluap.github.io/obs-picamera
Project-URL: Repository, https://github.com/gluap/obs-picamera
